contains_snippet/__init__.py
contains_snippet/__main__.py
contains_snippet/cli.py
contains_snippet/matcher.py
contains_snippet/py.typed
contains_snippet-20260108014512.dist-info/licenses/LICENSE.txt
contains_snippet-20260108014512.dist-info/METADATA
contains_snippet-20260108014512.dist-info/WHEEL
contains_snippet-20260108014512.dist-info/entry_points.txt
contains_snippet-20260108014512.dist-info/top_level.txt
contains_snippet-20260108014512.dist-info/RECORD
