Metadata-Version: 2.4
Name: contains-snippet
Version: 20260108014512
Summary: CLI tool to check if a snippet exists in files
Author-email: 10U Labs <dev@10ulabs.com>
License-Expression: Apache-2.0
Project-URL: Homepage, https://github.com/10U-Labs-LLC/contains-snippet
Project-URL: Issues, https://github.com/10U-Labs-LLC/contains-snippet/issues
Project-URL: Repository, https://github.com/10U-Labs-LLC/contains-snippet
Classifier: Development Status :: 4 - Beta
Classifier: Environment :: Console
Classifier: Intended Audience :: Developers
Classifier: Programming Language :: Python :: 3
Classifier: Programming Language :: Python :: 3.10
Classifier: Programming Language :: Python :: 3.11
Classifier: Programming Language :: Python :: 3.12
Classifier: Programming Language :: Python :: 3.13
Classifier: Topic :: Software Development :: Quality Assurance
Requires-Python: >=3.10
License-File: LICENSE.txt
Dynamic: license-file
